LICENSE
README.md
setup.py
assistant_fulfillment_helper/__init__.py
assistant_fulfillment_helper/fulfillment_helper.py
assistant_fulfillment_helper/fulfillment_helper_context.py
assistant_fulfillment_helper.egg-info/PKG-INFO
assistant_fulfillment_helper.egg-info/SOURCES.txt
assistant_fulfillment_helper.egg-info/dependency_links.txt
assistant_fulfillment_helper.egg-info/requires.txt
assistant_fulfillment_helper.egg-info/top_level.txt
assistant_fulfillment_helper/app/controllers/auth_controller.py
assistant_fulfillment_helper/app/controllers/webhook_controller.py
assistant_fulfillment_helper/app/data/token_data.py
assistant_fulfillment_helper/app/data/webhook_data.py
assistant_fulfillment_helper/app/exceptions/__init__.py
assistant_fulfillment_helper/app/exceptions/duplicated_intent_node_exception.py
assistant_fulfillment_helper/app/exceptions/intent_callback_not_found_exception.py
assistant_fulfillment_helper/app/exceptions/intent_response_instance_exception.py
assistant_fulfillment_helper/app/exceptions/invalid_webhook_token_exception.py
assistant_fulfillment_helper/app/exceptions/webhook_not_found_exception.py
assistant_fulfillment_helper/app/models/intent_model.py
assistant_fulfillment_helper/app/responses/fulfillment_helper_response.py
assistant_fulfillment_helper/app/server/__init__.py
assistant_fulfillment_helper/app/server/fulfillment_server.py
assistant_fulfillment_helper/app/server/routes.py
test/test_fulfillment_helper.py
test/test_fulfillment_helper_context.py
test/test_fulfillment_helper_response.py
test/test_webhook_request.py