Metadata-Version: 2.1
Name: assistant-fulfillment-helper
Version: 1.0.6
Summary: Assistant Fulfillment Helper Server
Home-page: https://github.com/totvslabs/assistant-fulfillment-helper
Author: TotvsLabs
Author-email: info@totvslabs.com
License: UNKNOWN
Keywords: assistant fulfillment helper carol totvs carolina carolapp
Platform: UNKNOWN
Requires-Python: >=3.7
